banded_matrices/.gitignore
banded_matrices/CMakeLists.txt
banded_matrices/__init__.py
banded_matrices/banded.py
banded_matrices/cc/.gitignore
banded_matrices/cc/CMakeLists.txt
banded_matrices/cc/googletest.CMakeLists.txt
banded_matrices/cc/include/banded_matrices/banded_matrix.hpp
banded_matrices/cc/include/banded_matrices/cholesky.hpp
banded_matrices/cc/include/banded_matrices/common.hpp
banded_matrices/cc/include/banded_matrices/product.hpp
banded_matrices/cc/include/banded_matrices/solve.hpp
banded_matrices/cc/include/banded_matrices/unary_broadcastable_op_kernel.hpp
banded_matrices/cc/src/banded_matrices/block_band.cc
banded_matrices/cc/src/banded_matrices/cholesky.cc
banded_matrices/cc/src/banded_matrices/inverse.cc
banded_matrices/cc/src/banded_matrices/outer_vec_vec.cc
banded_matrices/cc/src/banded_matrices/pack_matrix.cc
banded_matrices/cc/src/banded_matrices/product_band_band.cc
banded_matrices/cc/src/banded_matrices/product_band_mat.cc
banded_matrices/cc/src/banded_matrices/reverse_inverse.cc
banded_matrices/cc/src/banded_matrices/solve_triang_band.cc
banded_matrices/cc/src/banded_matrices/solve_triang_mat.cc
banded_matrices/cc/src/banded_matrices/square_band.cc
banded_matrices/cc/src/banded_matrices/symmetrise.cc
banded_matrices/cc/src/banded_matrices/transpose_band.cc
banded_matrices/cc/test/common.hpp
banded_matrices/cc/test/main.cc
banded_matrices/cc/test/test_banded_matrix.cc
banded_matrices/cc/test/test_product_band_band.cc
banded_matrices/cc/test/test_solve.cc
banded_matrices/library.py
banded_matrices/platform.py
banded_matrices/types.py
dummy.c
banded_matrices-0.1.3.dist-info/LICENCE
banded_matrices-0.1.3.dist-info/METADATA
banded_matrices-0.1.3.dist-info/WHEEL
banded_matrices-0.1.3.dist-info/RECORD
