Metadata-Version: 2.1
Name: banded_matrices
Version: 0.1.3
Summary: Native (C++) implementation of Banded Matrices for TensorFlow
Home-page: https://github.com/secondmind-labs/banded_matrices
License: Apache-2.0
Keywords: banded matrices,linear algebra
Author: Banded matrices contributors
Author-email: labs@secondmind.ai
Requires-Python: >=3.7,<3.12
Classifier: License :: OSI Approved :: Apache Software License
Classifier: Operating System :: OS Independent
Classifier: Programming Language :: Python :: 3
Classifier: Programming Language :: Python :: 3.7
Classifier: Programming Language :: Python :: 3.8
Classifier: Programming Language :: Python :: 3.9
Classifier: Programming Language :: Python :: 3.10
Classifier: Programming Language :: Python :: 3.11
Classifier: Programming Language :: Python :: 3.6
Classifier: Topic :: Scientific/Engineering :: Artificial Intelligence
Requires-Dist: cmake (>=3.18.0,<3.19.0)
Requires-Dist: importlib-metadata (>=4.4,<5.0)
Requires-Dist: numpy (>=1.18.0,<2.0.0)
Requires-Dist: tensorflow (>=2.4.0,<2.7.0) ; python_version >= "3.7" and python_version < "3.8"
Requires-Dist: tensorflow (>=2.4.0,<2.7.0) ; python_version >= "3.8" and python_version < "3.9"
Requires-Dist: tensorflow (>=2.5.0,<2.7.0) ; python_version >= "3.9" and python_version < "3.10"
Requires-Dist: tensorflow (>=2.7.0,<2.9.0) ; python_version >= "3.10" and python_version < "3.11"
Requires-Dist: tensorflow (>=2.8.0,<2.16.0) ; python_version >= "3.11" and python_version < "3.12"
Project-URL: Repository, https://github.com/secondmind-labs/banded_matrices
